{
  "version": "6",
  "dialect": "sqlite",
  "id": "b4f1468e-0ec8-4751-b898-897a752bdca1",
  "prevId": "00000000-0000-0000-0000-000000000000",
  "tables": {
    "posts": {
      "name": "posts",
      "columns": {
        "id": {
          "name": "id",
          "type": "text",
          "primaryKey": true,
          "notNull": true,
          "autoincrement": false
        },
        "url": {
          "name": "url",
          "type": "text(512)",
          "primaryKey": false,
          "notNull": false,
          "autoincrement": false
        },
        "authorId": {
          "name": "authorId",
          "type": "text",
          "primaryKey": false,
          "notNull": true,
          "autoincrement": false
        },
        "privacy": {
          "name": "privacy",
          "type": "text",
          "primaryKey": false,
          "notNull": false,
          "autoincrement": false
        },
        "replyToId": {
          "name": "replyToId",
          "type": "text",
          "primaryKey": false,
          "notNull": false,
          "autoincrement": false
        },
        "repostOfId": {
          "name": "repostOfId",
          "type": "text",
          "primaryKey": false,
          "notNull": false,
          "autoincrement": false
        },
        "createdAt": {
          "name": "createdAt",
          "type": "integer",
          "primaryKey": false,
          "notNull": true,
          "autoincrement": false
        },
        "deletedAt": {
          "name": "deletedAt",
          "type": "integer",
          "primaryKey": false,
          "notNull": false,
          "autoincrement": false
        }
      },
      "indexes": {},
      "foreignKeys": {
        "posts_authorId_users_id_fk": {
          "name": "posts_authorId_users_id_fk",
          "tableFrom": "posts",
          "tableTo": "users",
          "columnsFrom": [
            "authorId"
          ],
          "columnsTo": [
            "id"
          ],
          "onDelete": "no action",
          "onUpdate": "no action"
        },
        "posts_replyToId_posts_id_fk": {
          "name": "posts_replyToId_posts_id_fk",
          "tableFrom": "posts",
          "tableTo": "posts",
          "columnsFrom": [
            "replyToId"
          ],
          "columnsTo": [
            "id"
          ],
          "onDelete": "no action",
          "onUpdate": "no action"
        },
        "posts_repostOfId_posts_id_fk": {
          "name": "posts_repostOfId_posts_id_fk",
          "tableFrom": "posts",
          "tableTo": "posts",
          "columnsFrom": [
            "repostOfId"
          ],
          "columnsTo": [
            "id"
          ],
          "onDelete": "no action",
          "onUpdate": "no action"
        }
      },
      "compositePrimaryKeys": {},
      "uniqueConstraints": {}
    },
    "secrets": {
      "name": "secrets",
      "columns": {
        "key": {
          "name": "key",
          "type": "text",
          "primaryKey": true,
          "notNull": true,
          "autoincrement": false
        },
        "value": {
          "name": "value",
          "type": "text",
          "primaryKey": false,
          "notNull": true,
          "autoincrement": false
        }
      },
      "indexes": {},
      "foreignKeys": {},
      "compositePrimaryKeys": {},
      "uniqueConstraints": {}
    },
    "userFollows": {
      "name": "userFollows",
      "columns": {
        "id": {
          "name": "id",
          "type": "integer",
          "primaryKey": true,
          "notNull": true,
          "autoincrement": false
        },
        "followerId": {
          "name": "followerId",
          "type": "text",
          "primaryKey": false,
          "notNull": true,
          "autoincrement": false
        },
        "followeeId": {
          "name": "followeeId",
          "type": "text",
          "primaryKey": false,
          "notNull": true,
          "autoincrement": false
        },
        "followAt": {
          "name": "followAt",
          "type": "integer",
          "primaryKey": false,
          "notNull": true,
          "autoincrement": false
        }
      },
      "indexes": {},
      "foreignKeys": {
        "userFollows_followerId_users_id_fk": {
          "name": "userFollows_followerId_users_id_fk",
          "tableFrom": "userFollows",
          "tableTo": "users",
          "columnsFrom": [
            "followerId"
          ],
          "columnsTo": [
            "id"
          ],
          "onDelete": "no action",
          "onUpdate": "no action"
        },
        "userFollows_followeeId_users_id_fk": {
          "name": "userFollows_followeeId_users_id_fk",
          "tableFrom": "userFollows",
          "tableTo": "users",
          "columnsFrom": [
            "followeeId"
          ],
          "columnsTo": [
            "id"
          ],
          "onDelete": "no action",
          "onUpdate": "no action"
        }
      },
      "compositePrimaryKeys": {},
      "uniqueConstraints": {}
    },
    "users": {
      "name": "users",
      "columns": {
        "id": {
          "name": "id",
          "type": "text",
          "primaryKey": true,
          "notNull": true,
          "autoincrement": false
        },
        "username": {
          "name": "username",
          "type": "text(128)",
          "primaryKey": false,
          "notNull": true,
          "autoincrement": false
        },
        "hostname": {
          "name": "hostname",
          "type": "text(512)",
          "primaryKey": false,
          "notNull": false,
          "autoincrement": false
        },
        "password": {
          "name": "password",
          "type": "text(256)",
          "primaryKey": false,
          "notNull": false,
          "autoincrement": false
        },
        "nickname": {
          "name": "nickname",
          "type": "text(128)",
          "primaryKey": false,
          "notNull": true,
          "autoincrement": false
        },
        "bio": {
          "name": "bio",
          "type": "text(2048)",
          "primaryKey": false,
          "notNull": true,
          "autoincrement": false,
          "default": "''"
        },
        "url": {
          "name": "url",
          "type": "text(512)",
          "primaryKey": false,
          "notNull": false,
          "autoincrement": false
        },
        "privateKey": {
          "name": "privateKey",
          "type": "text(1024)",
          "primaryKey": false,
          "notNull": false,
          "autoincrement": false
        },
        "publicKey": {
          "name": "publicKey",
          "type": "text(1024)",
          "primaryKey": false,
          "notNull": false,
          "autoincrement": false
        },
        "createdAt": {
          "name": "createdAt",
          "type": "integer",
          "primaryKey": false,
          "notNull": true,
          "autoincrement": false
        },
        "deletedAt": {
          "name": "deletedAt",
          "type": "integer",
          "primaryKey": false,
          "notNull": false,
          "autoincrement": false
        }
      },
      "indexes": {},
      "foreignKeys": {},
      "compositePrimaryKeys": {},
      "uniqueConstraints": {}
    }
  },
  "enums": {},
  "_meta": {
    "schemas": {},
    "tables": {},
    "columns": {}
  },
  "internal": {
    "indexes": {}
  }
}